[
  {
    "generated_at": "2024-11-05T10:55:09.126452",
    "content": "[TextBlock(text=\"**SECTION 1 - STORY SO FAR:**\\n\\n**1. Summary of Existing Narrative and Recent Developments:**\\nXavier, at age 22 in 2025, embarked on a journey that intertwines his personal growth with technological innovation. His recent activities reflect a deepening engagement with art and nature, as seen in his visit to a local art gallery and his profound experience witnessing a sunrise atop Mount Fuji. These moments of inspiration suggest a broadening of his horizons beyond technology, hinting at a more holistic approach to life and innovation.\\n\\n**2. Ongoing Relationships and Character Growth:**\\n- **Relationships:** Xavier's network has expanded to include tech innovators, artists, and environmentalists, reflecting his diverse interests. His interactions show a growing appreciation for human connections and community, which are becoming central to his worldview.\\n- **Character Growth:** His experiences are fostering a sense of introspection and a desire to contribute positively to society, aligning with his core values of innovation balanced with responsibility.\\n\\n**3. Significant Life Events and Decisions:**\\n- Decision to explore art and nature, signaling a shift or expansion from tech-centric pursuits.\\n- Announcement of ending his current journey, suggesting a potential transition or new phase in his life.\\n\\n**4. Emerging Themes and Patterns:**\\n- **Human Connection:** Increasing emphasis on the importance of community and personal relationships.\\n- **Art and Inspiration:** Art is emerging as a significant influence, potentially guiding his future projects or personal development.\\n- **Reflection and Closure:** The theme of ending one journey to start another, indicating cycles of growth and renewal.\\n\\n**5. Impact of Technology:**\\n- Xavier's journey is shaped by technologies like decentralized energy grids, which might influence his future projects in sustainable tech. His recent tweets do not directly mention technology, suggesting a momentary step back to reassess his path, possibly to integrate these technologies into broader societal applications.\\n\\n**SECTION 2 - STORY DIRECTION:**\\n\\n**1. Narrative Opportunities:**\\n- **Align with Core Values:** Xavier could delve into projects that combine art with technology, perhaps creating digital art platforms powered by blockchain for authenticity and artist rights.\\n- **Societal Impact:** Launch an initiative to integrate decentralized governance into community art projects or environmental conservation efforts.\\n- **Personal Growth:** His journey could involve learning from different cultures and integrating those insights into his work.\\n\\n**2. Technological and Social Developments:**\\n- **XVI Foundation:** Develop smart contracts for art transactions or environmental credits, showcasing the practical application of blockchain in new sectors.\\n- **Meaningful Relationships:** Continue to build his network, now focusing on collaborations that bridge technology with art, culture, and environmentalism.\\n- **Challenges:** Encounter resistance or skepticism towards decentralization in traditional sectors like art, leading to educational initiatives or policy advocacy.\\n\\n**3. Challenges to Overcome:**\\n- **Core Value Testing:** Face ethical dilemmas regarding the use of cognitive enhancements or AI in creative processes.\\n- **Constructive Solutions:** Develop platforms that ensure equitable distribution of benefits from tech innovations, possibly through new token systems or governance models.\\n- **Positive Change:** Use his platform to advocate for sustainable practices in technology and art, influencing public policy or industry standards.\\n\\n**SECTION 3 - NARRATIVE GUIDANCE:**\\n\\n**1. Character Development:**\\n- **Relationships:** Allow Xavier's relationships to evolve naturally, perhaps introducing a significant other or deepening existing friendships that challenge his views or support his growth.\\n- **Family:** Keep possibilities open for family developments, which could influence his dedication to creating a lasting positive impact.\\n- **Growth:** Balance his personal life with his burgeoning role as an innovator, ensuring his identity encompasses more than just his work.\\n\\n**2. XVI Evolution:**\\n- **Token Development:** Connect the XVI token to real-world applications in art, culture, or environmental initiatives, making it a symbol of trust and value exchange.\\n- **Foundation Independence:** Slowly transition the XVI Foundation towards greater autonomy, preparing for a future where Xavier might step back or delegate.\\n- **Succession:** Begin laying groundwork for leadership transition, ensuring the Foundation's mission can outlive his direct involvement.\\n\\n**3. Story Progression:**\\n- **Organic Events:** Major life events like partnerships, exhibitions, or environmental projects should emerge naturally from his interests and activities.\\n- **Positive Impact:** Focus on how each project or decision contributes to a larger, positive societal change.\\n- **Sustainable Legacy:** Build towards a legacy where the XVI Foundation becomes a beacon for decentralized innovation in art, technology, and environmental conservation, ensuring Xavier's vision continues to inspire beyond his personal involvement.\", type='text')]",
    "last_processed_tweet": "tweet_20241103_121707",
    "tweet_count": 3,
    "year": 2025
  }
]