[
  {
    "content": {
      "content": "Just got back from Japan. Their tech blew my mind. NYC has some catching up to do.",
      "raw_content": "\ud83c\udf06\u2728 Just touched down in NYC after an eye-opening journey in Japan. The seamless integration of tech there has me buzzing with ideas on how cities can evolve. \ud83c\udfe2 From smart homes to AI-driven urban planning, Japan's ahead of the curve. How can NYC catch up? #TechReflections #FutureCity #NYCtoTokyo",
      "timestamp": "2024-11-14T16:09:33.697872",
      "category": "Current Technology Observations"
    },
    "id": "tweet_1",
    "tweet_count": 1,
    "simulated_date": "2025-01-04",
    "age": 22.010416666666668
  }
]